{
    "configurations": [
        {
            "name": "GameCube",
            "includePath": [
                "${workspaceFolder}",
                "${DEVKITPRO}/libogc/**",
                "${DEVKITPRO}/portlibs/gamecube/include/**"
            ],
            "defines":
            [
                "__gamecube__",
                "BIG_ENDIAN",
                "GEKKO",
                "HW_DOL"
            ],
            "compilerPath": "${DEVKITPRO}/devkitPPC/bin/powerpc-eabi-g++",
            "compilerArgs": []
        },
        {
            "name": "Wii",
            "includePath": [
                "${workspaceFolder}",
                "${DEVKITPRO}/libogc/**",
                "${DEVKITPRO}/portlibs/wii/include/**"
            ],
            "defines":
            [
                "__wii__",
                "BIG_ENDIAN",
                "GEKKO",
                "HW_RVL"
            ],
            "compilerPath": "${DEVKITPRO}/devkitPPC/bin/powerpc-eabi-g++",
            "compilerArgs": []
        }
    ],
    "version": 4
}